{
  "outDir": "./src/api",
  "templatePath": "./pontTemplate",
  "usingMultipleOrigins": true,
  "origins": [
    {
      "name": "acl",
      "originUrl": "http://127.0.0.1:7777/v3/api-docs/acl",
      "originType": "SwaggerV3",
      "usingOperationId": true
    },
    {
      "name": "auth",
      "originUrl": "http://127.0.0.1:7777/v3/api-docs/auth",
      "originType": "SwaggerV3",
      "usingOperationId": true
    },
    {
      "name": "code",
      "originUrl": "http://127.0.0.1:7777/v3/api-docs/dictionary",
      "originType": "SwaggerV3",
      "usingOperationId": true
    }
  ]
}
